compiler/__init__.py
compiler/lexemes.py
compiler/processor_config_schemas.py
compiler/repo_processor.py
compiler/runtime_variables.py
compiler/semantics.py
compiler/yamale_converter.py
compiler/yaml_augmentation.py
simple_grid_yaml_compiler/__init__.py
simple_grid_yaml_compiler/yaml_compiler.py
simple_grid_yaml_compiler/compiler/__init__.py
simple_grid_yaml_compiler/compiler/constants.py
simple_grid_yaml_compiler/compiler/lexemes.py
simple_grid_yaml_compiler/compiler/processor_config_schemas.py
simple_grid_yaml_compiler/compiler/repo_processor.py
simple_grid_yaml_compiler/compiler/runtime_variables.py
simple_grid_yaml_compiler/compiler/semantics.py
simple_grid_yaml_compiler/compiler/yamale_converter.py
simple_grid_yaml_compiler/compiler/yaml_augmentation.py
simple_grid_yaml_compiler-1.0.6.dist-info/LICENSE
simple_grid_yaml_compiler-1.0.6.dist-info/METADATA
simple_grid_yaml_compiler-1.0.6.dist-info/WHEEL
simple_grid_yaml_compiler-1.0.6.dist-info/entry_points.txt
simple_grid_yaml_compiler-1.0.6.dist-info/top_level.txt
simple_grid_yaml_compiler-1.0.6.dist-info/RECORD
