Metadata-Version: 2.1
Name: simple-grid-yaml-compiler
Version: 1.0.6
Summary: The YAML compiler for the SIMPLE Grid Framework
Home-page: https://github.com/WLCG-Lightweight-Sites/simple_grid_yaml_compiler
Author: Mayank Sharma
Author-email: mayank.sharma@cern.ch
License: Apache Software License
Platform: UNKNOWN
Classifier: License :: OSI Approved :: Apache Software License
Classifier: Programming Language :: Python
Classifier: Programming Language :: Python :: 2.6
Classifier: Programming Language :: Python :: 2.7
Requires-Dist: bleach (==3.1.0)
Requires-Dist: certifi (==2019.6.16)
Requires-Dist: chardet (==3.0.4)
Requires-Dist: docutils (==0.15.2)
Requires-Dist: idna (==2.8)
Requires-Dist: pkginfo (==1.5.0.1)
Requires-Dist: Pygments (==2.4.2)
Requires-Dist: python-dotenv (==0.11.0)
Requires-Dist: PyYAML (==3.12)
Requires-Dist: readme-renderer (==24.0)
Requires-Dist: requests (==2.22.0)
Requires-Dist: requests-toolbelt (==0.9.1)
Requires-Dist: ruamel.ordereddict (==0.4.13)
Requires-Dist: ruamel.yaml (==0.15.71)
Requires-Dist: six (==1.12.0)
Requires-Dist: tqdm (==4.33.0)
Requires-Dist: twine (==1.13.0)
Requires-Dist: typing (==3.7.4.1)
Requires-Dist: urllib3 (==1.25.3)
Requires-Dist: webencodings (==0.5.1)
